rtl/ADR_define.svh
`ifndef ADR_DEFINE
`define ADR_DEFINE

`define XLEN           32
`define NUM_REGS       32
`define REG_ADDR_LEN   $clog2(`NUM_REGS)
`define INST_LEN       32
`define ADDRESS_LEN    32
`define PC_LEN         32

`define R_ALU_OPCODE    7'b0110011
`define I_ALU_OPCODE    7'b0010011
`define I_LD_OPCODE     7'b0000011
`define S_ST_OPCODE     7'b0100011
`define B_BR_OPCODE     7'b1100011
`define J_JAL_OPCODE    7'b1101111
`define I_JALR_OPCODE   7'b1100111
`define U_LUI_OPCODE    7'b0110111
`define U_AUIPC_OPCODE  7'b0010111

`define I_ECALL_OPCODE   7'b1110011
`define I_EBREAK_OPCODE  7'b1110011

`define ADD_FUNC_3  3'b000
`define SUB_FUNC_3  3'b000
`define XOR_FUNC_3  3'b100
`define OR_FUNC_3   3'b110
`define AND_FUNC_3  3'b111
`define SLL_FUNC_3  3'b001
`define SRL_FUNC_3  3'b101
`define SRA_FUNC_3  3'b101
`define SLT_FUNC_3  3'b010
`define SLTU_FUNC_3 3'b011

//TODO: Finish FUNC3 bits for all other ops

`define SUB_FUNC_7  7'b0100000
`define SRA_FUNC_7  7'b0100000

typedef enum logic[5:0] {
 ADD, SUB, XOR, OR, AND, SLL, SRL, SRA, SLT, SLTU, 
 ADDI, XORI, ORI, ANDI, SLLI, SRLI, SRAI, SLIT, SLTUI,
 LB, LH, LW, LBU, LHU,
 SB, SH, SW,
 BEQ, BNE, BLT, BGE, BLTU, BGEU,
 JAL, JALR, 
 LUI, AUIPC,
 ECALL, EBREAK
} ADR_OPTYPE;

`endif

rtl/ADR_decode.sv
`include "ADR_define.svh"

module ADR_decode (
    input wire clk,
    input wire reset,
    input wire [`INST_LEN-1:0] if_de_inst_i,
    input wire [`PC_LEN-1:0] if_de_pc_i,
    input wire [`XLEN-1:0] regfile_de_data_a_i,
    input wire [`XLEN-1:0] regfile_de_data_b_i,
    output logic [5:0] de_ex_optype_o,
    output logic [`REG_ADDR_LEN-1:0] de_regfile_addr_a_o,
    output logic [`REG_ADDR_LEN-1:0] de_regfile_addr_b_o,
    output logic [`XLEN-1:0] de_ex_data_a_o,
    output logic [`XLEN-1:0] de_ex_data_b_o,
    output logic [`XLEN-1:0] de_ex_data_imm_o,
    output logic [`PC_LEN-1:0] de_ex_pc_o
);

// segment the 32 bit instruction into its corresponding fields
logic [6:0] segment_1 = if_de_inst_i[6:0];
logic [4:0] segment_2 = if_de_inst_i[11:7];
logic [2:0] segment_3 = if_de_inst_i[14:12];
logic [4:0] segment_4 = if_de_inst_i[19:15];
logic [4:0] segment_5 = if_de_inst_i[24:20];
logic [6:0] segment_6 = if_de_inst_i[31:25];

ADR_OPTYPE optype;
logic [6:0] opcode;
logic sign_bit;
logic [`XLEN-1:0] immediate;

assign opcode = segment_1;
assign sign_bit = segment_6[6];

// TODO: finish immediate generation
always_comb begin
  case(opcode)
    `I_ALU_OPCODE: immediate = {{20{sign_bit}}, {segment_5, segment_6}};
    default:   immediate = 32'b0;
  endcase
end

always_ff @( posedge clk ) begin
  if (reset) begin
    de_ex_pc_o <= 0;
  end 
  else begin
    de_ex_pc_o <= if_de_pc_i;
  end
end

endmodule

rtl/ADR_fetch.sv
`include "ADR_define.svh"

module ADR_fetch (
    input wire clk,
    input wire reset,
    output logic [`INST_LEN-1:0] if_de_inst_o,
    output logic [`PC_LEN-1:0] if_de_pc_o
);

/* verilator public */
logic [`PC_LEN-1:0] program_counter;
wire  [`PC_LEN-1:0] next_program_counter;

assign next_program_counter = program_counter + 1;
assign if_de_pc_o = program_counter;

always_ff @( posedge clk ) begin
  if (reset) begin
    program_counter <= 0;
  end 
  else begin
    program_counter <= next_program_counter;
  end
end

endmodule

rtl/ADR_regfile.sv
`include "ADR_define.svh"

module ADR_regfile (
    input wire clk,
    input wire reset,
    input wire[`REG_ADDR_LEN-1:0] read_addr_a_i,
    input wire[`REG_ADDR_LEN-1:0] read_addr_b_i,
    input wire[`REG_ADDR_LEN-1:0] write_addr_i,
    input wire[`XLEN-1:0] write_data_i,
    output logic[`XLEN-1:0] read_data_a_o,
    output logic[`XLEN-1:0] read_data_b_o
    );

logic [31:0] register_file[0:31];

always_ff @( posedge clk ) begin
  read_data_a_o <= register_file[read_addr_a_i];
  read_data_b_o <= register_file[read_addr_b_i];
  register_file[write_addr_i] <= write_data_i;  
end

endmodule

rtl/ADR_core.sv
`include "ADR_define.svh"

module ADR_core (
    input wire clk,
    input wire reset
);

// REGFILE WIRES
logic[`XLEN-1:0] read_data_a, read_data_b, write_data;
logic[`REG_ADDR_LEN-1:0] read_addr_a, read_addr_b, write_addr;

// FETCH WIRES
logic [`INST_LEN-1:0] if_de_inst;
logic [`PC_LEN-1:0]   if_de_pc;

// DECODE WIRES
logic [5:0]          de_ex_optype;
logic [`XLEN-1:0]    de_ex_data_a, de_ex_data_b, de_ex_data_imm;
logic [`PC_LEN-1:0]  de_ex_pc;

ADR_regfile register_file
(
  .clk (clk),
  .reset (reset),
  .read_addr_a_i(read_addr_a),
  .read_addr_b_i(read_addr_b),
  .read_data_a_o(read_data_a),
  .read_data_b_o(read_data_b),
  .write_addr_i(write_addr),
  .write_data_i(write_data)
);

ADR_fetch fetch(
  .clk (clk),
  .reset (reset),
  .if_de_inst_o(if_de_inst),
  .if_de_pc_o(if_de_pc)
);

ADR_decode decode(
  .clk (clk),
  .reset (reset),
  .if_de_inst_i(if_de_inst),
  .if_de_pc_i(if_de_pc),
  .regfile_de_data_a_i(read_data_a),
  .regfile_de_data_b_i(read_data_b),
  .de_regfile_addr_a_o(read_addr_a),
  .de_regfile_addr_b_o(read_addr_b),
  .de_ex_data_a_o(de_ex_data_a),
  .de_ex_data_b_o(de_ex_data_b),
  .de_ex_data_imm_o(de_ex_data_imm),
  .de_ex_pc_o(de_ex_pc),
  .de_ex_optype_o(de_ex_optype)
);



endmodule

rtlsim/waveform.vcd
$version Generated by VerilatedVcd $end
$timescale 1ps $end

 $scope module TOP $end
  $var wire  1 H clk $end
  $var wire  1 I reset $end
  $scope module ADR_core $end
   $var wire  1 H clk $end
   $var wire 32 P de_ex_data_a [31:0] $end
   $var wire 32 Q de_ex_data_b [31:0] $end
   $var wire 32 R de_ex_data_imm [31:0] $end
   $var wire  6 O de_ex_optype [5:0] $end
   $var wire 32 & de_ex_pc [31:0] $end
   $var wire 32 N if_de_inst [31:0] $end
   $var wire 32 % if_de_pc [31:0] $end
   $var wire  5 K read_addr_a [4:0] $end
   $var wire  5 L read_addr_b [4:0] $end
   $var wire 32 # read_data_a [31:0] $end
   $var wire 32 $ read_data_b [31:0] $end
   $var wire  1 I reset $end
   $var wire  5 M write_addr [4:0] $end
   $var wire 32 J write_data [31:0] $end
   $scope module decode $end
    $var wire  1 H clk $end
    $var wire 32 P de_ex_data_a_o [31:0] $end
    $var wire 32 Q de_ex_data_b_o [31:0] $end
    $var wire 32 R de_ex_data_imm_o [31:0] $end
    $var wire  6 O de_ex_optype_o [5:0] $end
    $var wire 32 & de_ex_pc_o [31:0] $end
    $var wire  5 K de_regfile_addr_a_o [4:0] $end
    $var wire  5 L de_regfile_addr_b_o [4:0] $end
    $var wire 32 N if_de_inst_i [31:0] $end
    $var wire 32 % if_de_pc_i [31:0] $end
    $var wire 32 [ immediate [31:0] $end
    $var wire  7 S opcode [6:0] $end
    $var wire  6 Y optype [5:0] $end
    $var wire 32 # regfile_de_data_a_i [31:0] $end
    $var wire 32 $ regfile_de_data_b_i [31:0] $end
    $var wire  1 I reset $end
    $var wire  7 S segment_1 [6:0] $end
    $var wire  5 T segment_2 [4:0] $end
    $var wire  3 U segment_3 [2:0] $end
    $var wire  5 V segment_4 [4:0] $end
    $var wire  5 W segment_5 [4:0] $end
    $var wire  7 X segment_6 [6:0] $end
    $var wire  1 Z sign_bit $end
   $upscope $end
   $scope module fetch $end
    $var wire  1 H clk $end
    $var wire 32 N if_de_inst_o [31:0] $end
    $var wire 32 % if_de_pc_o [31:0] $end
    $var wire 32 ' next_program_counter [31:0] $end
    $var wire 32 % program_counter [31:0] $end
    $var wire  1 I reset $end
   $upscope $end
   $scope module register_file $end
    $var wire  1 H clk $end
    $var wire  5 K read_addr_a_i [4:0] $end
    $var wire  5 L read_addr_b_i [4:0] $end
    $var wire 32 # read_data_a_o [31:0] $end
    $var wire 32 $ read_data_b_o [31:0] $end
    $var wire 32 ( register_file[0] [31:0] $end
    $var wire 32 2 register_file[10] [31:0] $end
    $var wire 32 3 register_file[11] [31:0] $end
    $var wire 32 4 register_file[12] [31:0] $end
    $var wire 32 5 register_file[13] [31:0] $end
    $var wire 32 6 register_file[14] [31:0] $end
    $var wire 32 7 register_file[15] [31:0] $end
    $var wire 32 8 register_file[16] [31:0] $end
    $var wire 32 9 register_file[17] [31:0] $end
    $var wire 32 : register_file[18] [31:0] $end
    $var wire 32 ; register_file[19] [31:0] $end
    $var wire 32 ) register_file[1] [31:0] $end
    $var wire 32 < register_file[20] [31:0] $end
    $var wire 32 = register_file[21] [31:0] $end
    $var wire 32 > register_file[22] [31:0] $end
    $var wire 32 ? register_file[23] [31:0] $end
    $var wire 32 @ register_file[24] [31:0] $end
    $var wire 32 A register_file[25] [31:0] $end
    $var wire 32 B register_file[26] [31:0] $end
    $var wire 32 C register_file[27] [31:0] $end
    $var wire 32 D register_file[28] [31:0] $end
    $var wire 32 E register_file[29] [31:0] $end
    $var wire 32 * register_file[2] [31:0] $end
    $var wire 32 F register_file[30] [31:0] $end
    $var wire 32 G register_file[31] [31:0] $end
    $var wire 32 + register_file[3] [31:0] $end
    $var wire 32 , register_file[4] [31:0] $end
    $var wire 32 - register_file[5] [31:0] $end
    $var wire 32 . register_file[6] [31:0] $end
    $var wire 32 / register_file[7] [31:0] $end
    $var wire 32 0 register_file[8] [31:0] $end
    $var wire 32 1 register_file[9] [31:0] $end
    $var wire  1 I reset $end
    $var wire  5 M write_addr_i [4:0] $end
    $var wire 32 J write_data_i [31:0] $end
   $upscope $end
  $upscope $end
 $upscope $end
$enddefinitions $end


#0
b00000000000000000000000000000000 #
b00000000000000000000000000000000 $
b00000000000000000000000000000000 %
b00000000000000000000000000000000 &
b00000000000000000000000000000001 '
b00000000000000000000000000000000 (
b00000000000000000000000000000000 )
b00000000000000000000000000000000 *
b00000000000000000000000000000000 +
b00000000000000000000000000000000 ,
b00000000000000000000000000000000 -
b00000000000000000000000000000000 .
b00000000000000000000000000000000 /
b00000000000000000000000000000000 0
b00000000000000000000000000000000 1
b00000000000000000000000000000000 2
b00000000000000000000000000000000 3
b00000000000000000000000000000000 4
b00000000000000000000000000000000 5
b00000000000000000000000000000000 6
b00000000000000000000000000000000 7
b00000000000000000000000000000000 8
b00000000000000000000000000000000 9
b00000000000000000000000000000000 :
b00000000000000000000000000000000 ;
b00000000000000000000000000000000 <
b00000000000000000000000000000000 =
b00000000000000000000000000000000 >
b00000000000000000000000000000000 ?
b00000000000000000000000000000000 @
b00000000000000000000000000000000 A
b00000000000000000000000000000000 B
b00000000000000000000000000000000 C
b00000000000000000000000000000000 D
b00000000000000000000000000000000 E
b00000000000000000000000000000000 F
b00000000000000000000000000000000 G
1H
0I
b00000000000000000000000000000000 J
b00000 K
b00000 L
b00000 M
b00000000000000000000000000000000 N
b000000 O
b00000000000000000000000000000000 P
b00000000000000000000000000000000 Q
b00000000000000000000000000000000 R
b0000000 S
b00000 T
b000 U
b00000 V
b00000 W
b0000000 X
b000000 Y
0Z
b00000000000000000000000000000000 [
#1
0H
#2
b00000000000000000000000000000001 %
b00000000000000000000000000000010 '
1H
#3
0H
#4
b00000000000000000000000000000010 %
b00000000000000000000000000000001 &
b00000000000000000000000000000011 '
1H
#5
0H
#6
b00000000000000000000000000000011 %
b00000000000000000000000000000010 &
b00000000000000000000000000000100 '
1H
#7
0H
#8
b00000000000000000000000000000100 %
b00000000000000000000000000000011 &
b00000000000000000000000000000101 '
1H
#9
0H
#10
b00000000000000000000000000000101 %
b00000000000000000000000000000100 &
b00000000000000000000000000000110 '
1H
#11
0H
#12
b00000000000000000000000000000110 %
b00000000000000000000000000000101 &
b00000000000000000000000000000111 '
1H
#13
0H
#14
b00000000000000000000000000000111 %
b00000000000000000000000000000110 &
b00000000000000000000000000001000 '
1H
#15
0H
#16
b00000000000000000000000000001000 %
b00000000000000000000000000000111 &
b00000000000000000000000000001001 '
1H
#17
0H
#18
b00000000000000000000000000001001 %
b00000000000000000000000000001000 &
b00000000000000000000000000001010 '
1H
